{
  "pt": [
    {
      "name": "",
      "description": "Disposto a fazer qualquer coisa para fechar uma venda e/ou agradar os superiores"
    },
    {
      "name": "",
      "description": "Resistência a germes, vírus, fungos e a maioria das outras ameaças à saúde"
    },
    {
      "name": "",
      "description": "Habilidade de elevar e diminuir o próprio colesterol por vontate própria"
    },
    {
      "name": "",
      "description": "Outros demais para mencionar"
    }
  ],
  "en": [
    {
      "name": "",
      "description": "Willingness to do anything to close a sale and/or please higher-ups"    
    },
    {
      "name": "",
      "description": "Resistance to germs, viruses, fungi, and most other health threats"
    },
    {
      "name": "",
      "description": "Ability to raise and lower own cholesterol at will"
    },
    {
      "name": "",
      "description": "Others too numerous to mention"
    }
  ]
}
